{"parse":{"title":"Template:CeVIO","pageid":117677,"wikitext":{"*":"<noinclude>[[Category:\u6b4c\u624b\u6a21\u677f]]</noinclude>\n\n{{Navbox\n|name  = CeVIO\n|title = [[CeVIO]]\n|basestyle = background:#ee87b4;color:white;\n|groupstyle = background:#7dcef4;color:white;\n|liststyle = line-height:1.4em;\n\n| group1  = \u672c\u5bb6\n| list1   = [[\u4f50\u85e4\u838e\u838e\u62c9|\u3055\u3068\u3046\u3055\u3055\u3089\uff08\u4f50\u85e4\u838e\u838e\u62c9\uff09]] \u2022 <!--\n         -->[[\u94c3\u6728\u6893\u6893\u5f25|\u3059\u305a\u304d\u3064\u3065\u307f\uff08\u94c3\u6728\u6893\u6893\u5f25\uff09]] \u2022 <!--\n         -->[[\u9ad8\u6865(CeVIO)|\u30bf\u30ab\u30cf\u30b7\uff08\u9ad8\u6865\uff09]]\n\n| group2  = [[Color Voice Series]]\n| list2   =  [[\u8d64\u54b2\u6e4a]] \u2022 <!--\n         -->[[\u7eff\u54b2\u9999\u6f84]] \u2022 <!--\n         -->[[\u94f6\u54b2\u5927\u548c]] \u2022 <!--\n         -->[[\u91d1\u54b2\u5c0f\u6625]] \u2022 <!--\n         -->[[\u767d\u54b2\u4f18\u5927]] \u2022 <!--\n         -->[[\u9ec4\u54b2\u7231\u91cc]]\n\n| group3  = 1st PLACE\n| list3   = [[ONE -ARIA ON THE PLANETES-]] \u2022 <!--\n         -->[[IA|IA -ARIA ON THE PLANETES-]]\n\n| group4  = \u5176\u4ed6\n| list4   = [[HAL-O-ROID]]\n\n}}"}}}