{"parse":{"title":"Template:Editnotices/Namespace/MediaWiki","pageid":98511,"wikitext":{"*":"{{info\n|color=red\n|leftimage=[[image:Gnome-emblem-important.svg|75px|link=]]\n|<big><center>'''\u60a8\u6b63\u5728{{color|red|\u7f16\u8f91MediaWiki\u754c\u9762}}\u201cMediaWiki:{{PAGENAME}}\u201d'''</center></big>\n*\u60a8\u6b63\u5728\u7f16\u8f91'''MediaWiki\u754c\u9762'''\u3002\u5982\u679c\u60a8\u5e76\u4e0d\u6e05\u695a\u81ea\u5df1\u5728\u505a\u4ec0\u4e48\uff0c\u8bf7{{color|red|\u5173\u95ed\u8fd9\u4e2a\u9875\u9762\u6216\u8fd4\u56de\u4e0a\u4e00\u9875}}\uff1b\n*\u4fee\u6539\u8fd9\u4e2a\u9875\u9762\u4f1a\u5f71\u54cd'''\u840c\u5a18\u767e\u79d1'''\u4e0a\u7684\u754c\u9762\u663e\u793a\uff0c\u8fd9\u662f\u4e00\u4e2a\u91cd\u5927\u7684\u6539\u52a8\uff1b\n**\u5728\u4fee\u6539MediaWiki\u663e\u793a\u65f6\uff0c\u60a8\u5e94\u6ce8\u610f\u8bed\u8a00\u4e4b\u95f4\u7684\u6620\u5c04\u5173\u7cfb\uff0c\u8be6\u89c1 '''[//zh.moegirl.org/User:\u5c0f\u6728\u66fe%20\u96ea\u83dc \u7528\u6237\u754c\u9762\u64b0\u5199\u6307\u5f15]'''\u4e2d\u7684\u4ecb\u7ecd\uff1b\n*{{color|red|'''\u9519\u8bef\u5730\u7f16\u8f91\u8fd9\u4e2a\u9875\u9762\u53ef\u80fd\u4f1a\u5e26\u6765\u4e25\u91cd\u540e\u679c\uff01\u60a8\u5fc5\u987b\u7ecf\u8fc7\u53cd\u590d\u6d4b\u8bd5\u786e\u8ba4\u66f4\u6539\u65e0\u8bef\uff1b'''}}\n*[https://translatewiki.net translatewiki.net] \u4e0a\u7684\u201cMediaWiki\u672c\u5730\u5316\u8ba1\u5212\u201d\u53ef\u4f9b\u60a8\u66f4\u65b0MediaWiki\u8f6f\u4ef6\u7684\u7ffb\u8bd1\u95ee\u9898\u3002\n}}"}}}