{"parse":{"title":"Template:LyricsKai/colors","pageid":274750,"wikitext":{"*":"<includeonly><templatestyles src=\"Template:LyricsKai/colors/styles.css\" /><!--\n-->{{#vardefine:lyricsKai/colors.hasRuby|{{#invoke:Lyrics/colors|main|arrayName= lyricsKai/colors.original\n|colors={{{colors|}}}\n|charas={{{charas|}}}\n|charaBlock={{{charaBlock|}}}\n|lyric={{{original|}}}}}<!--\n-->{{#ifeq:{{{traColors|}}}|on|{{#invoke:Lyrics/colors|main|arrayName= lyricsKai/colors.translated\n|colors={{{colors|}}}\n|charas={{{charas|}}}\n|charaBlock={{{charaBlock|}}}\n|lyric={{{translated|}}}}}\n}}}}<!--\n-->{{#ifeq:{{{charaBlock|}}}|on\n|<p>{{#invoke:Lyrics/colors/sub|charaBlock|colors={{{colors|}}}|charas={{{charas|}}}|groupName={{{groupName|}}}|groupColor={{{lstyle|}}}}}</p>}}<!--\n-->{{LyricsKai|colorsMode={{#ifeq:{{{traColors|}}}|on|2|1}}|hasRuby={{#var:lyricsKai/colors.hasRuby}}|lstyle={{{lstyle|}}}|rstyle={{{rstyle|}}}|llang={{{llang|}}}|rlang={{{rlang|}}}|width={{{width|}}}\n|reserveWidth={{{reserveWidth|0px}}}|minWidth={{{minWidth|300px}}}|containerstyle={{{containerstyle|}}}\n|translated={{#ifeq:{{{traColors|}}}|on||{{{translated|}}}}}}}</includeonly><noinclude>{{doc}}</noinclude>"}}}