{"parse":{"title":"Template:T7s\u4eba\u7269/Row titlestyle","pageid":110941,"wikitext":{"*":"<includeonly>style=\"font-size:85%; padding:2px; border:3px; border-style:solid; border-radius:10px; {{#if:{{{\u5076\u50cf\u5c5e\u6027|}}} | {{#ifeq:{{{\u5076\u50cf\u5c5e\u6027|}}}|vocalist| background:#ffedf2; color:#FF007F;|}} {{#ifeq:{{{\u5076\u50cf\u5c5e\u6027|}}}|variety idol| background:#E6CFE6; color:#8B00FF;|}} {{#ifeq:{{{\u5076\u50cf\u5c5e\u6027|}}}|dancer| background:#E0FFFF; color:#1E90FF;|}} {{#ifeq:{{{\u5076\u50cf\u5c5e\u6027|}}}|model| background:#F5FFFA; color:#008000;|}} {{#ifeq:{{{\u5076\u50cf\u5c5e\u6027|}}}|player|background:#FFFDD0;color:#FF9900;|}} | background:#E0FFFF; color:#1E90FF; }}\"</includeonly>"}}}