{"parse":{"title":"Template:\u4e2d\u5b66\u62df\u4eba","pageid":79504,"wikitext":{"*":"<noinclude>\n\u8fd9\u91cc\u662f'''[[\u6a21\u677f:\u5b66\u6821\u62df\u4eba|\u4e16\u754c\u5b66\u6821\u62df\u4eba\u5316\u840c\u5a18]]'''\u5927\u5bb6\u65cf\u6a21\u677f\u4e2d\u7684'''\u4e2d\u5b66\u62df\u4eba'''\uff08\u5305\u62ec\u521d\u4e2d\u3001\u9ad8\u4e2d\u3001\u4ee5\u53ca\u521d\u9ad8\u4e2d\u4e00\u8d2f\u5236\u5b66\u6821\uff09\u3002\n\n\u6709\u7231\u7f16\u5199\u4e86\u81ea\u5df1\u7684\u4e2d\u5b66\u6bcd\u6821\u6761\u76ee\u7684\uff0c\u8bf7\u81ea\u884c\u5728\u6b64\u6a21\u677f\u4e2d\u52a0\u5165\u94fe\u63a5\u3002\n\n'''\u7531\u4e8e\u5b66\u6821\u4f17\u591a\uff0c\u8bf7\u52ff\u5411\u6b64\u6a21\u677f\u6dfb\u52a0\u672a\u521b\u5efa\u7684\u8bcd\u6761\u94fe\u63a5'''\n\n[[\u5206\u7c7b:\u840c\u5a18\u5316\u5bfc\u822a\u6a21\u677f]][[\u5206\u7c7b:\u5b66\u6821\u5a18\u5316]]\n</noinclude>{{Navbox\n| {{#ifeq:{{{1}}}|child|child|}}\n|name = \u4e2d\u5b66\u62df\u4eba\n|title = [[\u6a21\u677f:\u4e2d\u5b66\u62df\u4eba|<small>\u4e2d\u5b66\u62df\u4eba\uff08\u5305\u62ec\u521d\u4e2d\u3001\u9ad8\u4e2d\uff09\uff08''\u659c\u4f53''\u8868\u793a\u521d\u4e2d\uff0c<u>\u4e0b\u5212\u7ebf</u>\u8868\u793a\u521d\u9ad8\u4e2d\u4e00\u8d2f\u5236\u5b66\u6821\uff09</small>]]\n|state =  {{#ifeq:{{{2}}}|uncollapsed|mw-uncollapsed|mw-collapsible mw-collapsed}}\n|navbar = {{#ifeq:{{{1}}}|child|plain|}}\n\n|liststyle = width: auto;\n|groupstyle = width:3em\n\n| group1  = \u5927\u4e2d\u534e\u5730\u533a\n| list1   = {{Navbox subgroup\n  |group1 = \u5357\u65b9\u5730\u533a\n  |list1  = {{Navbox subgroup\n    |group1= \u6210\u90fd\u5b66\u6821\u62df\u4eba\u4f01\u5212\n    |list1= [[\u67e9\u671b|\u4e5d\u5916\u5a18(\u67e9\u671b)]] \u2022 <!--\n         -->[[\u4e25\u94b1\u591a\u591a|\u6210\u5916\u5a18(\u4e25\u94b1\u591a\u591a)]] \u2022 <!--\n         -->[[\u4e25\u960e|\u5b9e\u5916\u5a18(\u4e25\u960e)]]\n\n    |group2= \u5e7f\u4e1c\u5730\u533a\n    |list2= [[\u534e\u9644\u5a18]] \u2022 <!--\n         -->[[\u6df1\u4e2d\u5a18]] \u2022 <!--\n         -->[[\u91d1\u4e2d\u5a18]] \u2022 <!--\n         -->[[\u6df1\u5733\u5916\u56fd\u8bed\u5b66\u6821\u5a18]] \u2022 <!--\n         -->[[\u5e7f\u5dde\u6267\u4fe1\u4e2d\u5b66\u5a18]] \u2022 <!--\n         -->[[\u5e7f\u4e1c\u5e7f\u96c5\u4e2d\u5b66\u5a18]] \u2022 <!--\n         -->[[\u5e7f\u5dde\u5916\u56fd\u8bed\u5b66\u6821\u5a18]] \u2022 <!--\n         -->[[\u5e7f\u4e1c\u4ef2\u5143\u4e2d\u5b66\u5a18]] \u2022 <!--\n         -->[[\u5e7f\u5dde\u4e8c\u4e2d\u5a18]] \u2022 <!--\n         -->[[\u4fe1\u5b9c\u4e2d\u5b66\u5a18]] \u2022 <!--\n         -->[[\u6c55\u5934\u4e00\u4e2d\u5a18]] \u2022 <!--\n         -->[[\u807f\u6000\u5a18]] \u2022 <!--\n         --><u>[[\u6f6e\u5b9e\u5a18]]</u> \u2022 <!--\n         -->''[[\u9f99\u5b9e\u5a18]]'' \u2022 <!--\n         -->''[[\u8354\u6e7e\u5e7f\u96c5\u5a18]]'' \u2022 <!--\n         -->''[[\u767d\u4e91\u5e7f\u96c5\u5a18]]''\u2022 <!--\n         -->''[[\u9633\u4e1c\u5e7f\u96c5\u5a18]]''\u2022 <!--\n         -->''[[\u4e1c\u6c5f\u5e7f\u96c5\u5a18]]''\n\n    |group3= \u5176\u4ed6\u7701\u5e02\n    |list3=[[\u6cc9\u5dde\u7b2c\u4e94\u4e2d\u5b66\u5a18]] \u2022 <!--\n         -->[[\u676d\u5dde\u7b2c\u5341\u56db\u4e2d\u5b66\u5a18]] \u2022 <!--\n         -->[[\u5cb3\u9633\u53bf\u4e8c\u4e2d\u5a18]]\n\n    }}\n\n  |group2 = \u5317\u65b9\u5730\u533a\n  |list2  =[[\u90af\u90f8\u5e02\u7b2c\u4e00\u4e2d\u5b66\u5a18]]\n\n  |group3 = \u897f\u5317\u5730\u533a\n  |list3  = \uff08\u5f85\u8865\u5b8c\uff09\n\n  |group4 = \u9752\u85cf\u5730\u533a\n  |list4  = \uff08\u5f85\u8865\u5b8c\uff09\n\n  |group5 = \u6e2f\u6fb3\u53f0\u5730\u533a\n  |list5  = \uff08\u5f85\u8865\u5b8c\uff09\n  }}\n\n| group2  = \u65e5\u672c\u5730\u533a\n| list2   = \uff08\u5f85\u8865\u5b8c\uff09\n\n| group3  = \u4e9a\u6d32\u5176\u4ed6\u5730\u533a\n| list3   = \uff08\u5f85\u8865\u5b8c\uff09\n\n| group4  = \u5317\u7f8e\u5730\u533a\n| list4   = \uff08\u5f85\u8865\u5b8c\uff09\n\n| group5  = \u6b27\u6d32\u5730\u533a\n| list5   = \uff08\u5f85\u8865\u5b8c\uff09\n\n| group6  = \u5176\u4ed6\u5730\u533a\n| list6   = \uff08\u5f85\u8865\u5b8c\uff09\n}}"}}}