{"parse":{"title":"Template:\u70bc\u91d1\u5de5\u4f5c\u5ba4/\u6b63\u4f20","pageid":232019,"wikitext":{"*":"[[\u5206\u7c7b:\u4ee5\u7cfb\u5217\u5f52\u7eb3\u7684\u65e5\u672c\u52a8\u6f2b\u5bfc\u822a\u6a21\u677f]][[\u5206\u7c7b:\u70bc\u91d1\u5de5\u4f5c\u5ba4]]\n{{Navbox\n|name = \u70bc\u91d1\u5de5\u4f5c\u5ba4/\u6b63\u4f20\n|title = \u70bc\u91d1\u5de5\u4f5c\u5ba4\u6b63\u4f20\n|liststyle = line-height:1.4em;\n|titlestyle = background:#5CACEE;\n|groupstyle = background:#5CACEE;\n|belowstyle = background:#5CACEE;\n|group1=\u6b63\u4f20\n|list1={{Navbox\n        |child\n        |name = \u70bc\u91d1\u5de5\u4f5c\u5ba4/\u6b63\u4f20\n        |liststyle = line-height:1.4em;\n        |titlestyle = background:#5CACEE;\n        |groupstyle = background:#5CACEE;\n        |belowstyle = background:#5CACEE;\n        |list1= {{\u70bc\u91d1\u5de5\u4f5c\u5ba4/\u739b\u8389\u7684\u5de5\u4f5c\u5ba4|child|{{#switch:{{{1}}}|\u739b\u8389=uncollapsed|alluncollapsed=uncollapsed|collapsed}}}}\n        |list2= {{\u70bc\u91d1\u5de5\u4f5c\u5ba4/\u827e\u8389\u7684\u5de5\u4f5c\u5ba4|child|{{#switch:{{{1}}}|\u827e\u8389=uncollapsed|alluncollapsed=uncollapsed|collapsed}}}}\n        |list3= {{\u70bc\u91d1\u5de5\u4f5c\u5ba4/\u8389\u8389\u7684\u5de5\u4f5c\u5ba4|child|{{#switch:{{{1}}}|\u8389\u8389=uncollapsed|alluncollapsed=uncollapsed|collapsed}}}}\n        |list4= {{\u70bc\u91d1\u5de5\u4f5c\u5ba4/\u5c24\u8482\u7684\u5de5\u4f5c\u5ba4|child|{{#switch:{{{1}}}|\u5c24\u8482=uncollapsed|alluncollapsed=uncollapsed|collapsed}}}}\n        |list5= {{\u70bc\u91d1\u5de5\u4f5c\u5ba4/\u8587\u6b27\u857e\u7279\u7684\u5de5\u4f5c\u5ba4|child|{{#switch:{{{1}}}|\u8587\u6b27\u857e\u7279=uncollapsed|alluncollapsed=uncollapsed|collapsed}}}}\n        |list6= {{\u70bc\u91d1\u5de5\u4f5c\u5ba4/\u4f0a\u8389\u65af\u7684\u5de5\u4f5c\u5ba41|child|{{#switch:{{{1}}}|\u4f0a\u8389\u65af=uncollapsed|alluncollapsed=uncollapsed|collapsed}}}}\n        |list7= {{\u70bc\u91d1\u5de5\u4f5c\u5ba4/\u4f0a\u8389\u65af\u7684\u5de5\u4f5c\u5ba42|child|{{#switch:{{{1}}}|\u4f0a\u8389\u65af=uncollapsed|alluncollapsed=uncollapsed|collapsed}}}}\n        |list8= {{\u70bc\u91d1\u5de5\u4f5c\u5ba4/\u4f0a\u8389\u65af\u7684\u5de5\u4f5c\u5ba43|child|{{#switch:{{{1}}}|\u4f0a\u8389\u65af=uncollapsed|alluncollapsed=uncollapsed|collapsed}}}}\n        |list9= {{\u70bc\u91d1\u5de5\u4f5c\u5ba4/\u739b\u5a1c\u4f20\u59471|child|{{#switch:{{{1}}}|\u739b\u5a1c=uncollapsed|alluncollapsed=uncollapsed|collapsed}}}}\n        |list10= {{\u70bc\u91d1\u5de5\u4f5c\u5ba4/\u739b\u5a1c\u4f20\u59472|child|{{#switch:{{{1}}}|\u739b\u5a1c\u4f20\u5947=uncollapsed|alluncollapsed=uncollapsed|collapsed}}}}\n        |list11= {{\u70bc\u91d1\u5de5\u4f5c\u5ba4/\u7f57\u7f57\u5a1c\u7684\u5de5\u4f5c\u5ba4|child|{{#switch:{{{1}}}|\u7f57\u7f57\u5a1c=uncollapsed|alluncollapsed=uncollapsed|collapsed}}}}\n        |list12= {{\u70bc\u91d1\u5de5\u4f5c\u5ba4/\u6258\u6258\u8389\u7684\u5de5\u4f5c\u5ba4|child|{{#switch:{{{1}}}|\u6258\u6258\u8389=uncollapsed|alluncollapsed=uncollapsed|collapsed}}}}\n        |list13= {{\u70bc\u91d1\u5de5\u4f5c\u5ba4/\u6885\u9732\u9732\u7684\u5de5\u4f5c\u5ba4|child|{{#switch:{{{1}}}|\u6885\u9732\u9732=uncollapsed|alluncollapsed=uncollapsed|collapsed}}}}\n        |list14= {{\u70bc\u91d1\u5de5\u4f5c\u5ba4/\u7231\u590f\u7684\u5de5\u4f5c\u5ba4|child|{{#switch:{{{1}}}|\u7231\u590f=uncollapsed|alluncollapsed=uncollapsed|collapsed}}}}\n        |list15= {{\u70bc\u91d1\u5de5\u4f5c\u5ba4/\u827e\u65af\u5361\u4e0e\u7f57\u5409\u7684\u5de5\u4f5c\u5ba4|child|{{#switch:{{{1}}}|\u7231\u4e1d\u5361&\u7f57\u5409=uncollapsed|alluncollapsed=uncollapsed|collapsed}}}}\n        |list16= {{\u70bc\u91d1\u5de5\u4f5c\u5ba4/\u590f\u8389\u7684\u5de5\u4f5c\u5ba4|child|{{#switch:{{{1}}}|\u590f\u8389=uncollapsed|alluncollapsed=uncollapsed|collapsed}}}}\n        |list17= {{\u70bc\u91d1\u5de5\u4f5c\u5ba4/\u7d22\u83f2\u7684\u5de5\u4f5c\u5ba4|child|{{#switch:{{{1}}}|\u7d22\u83f2=uncollapsed|alluncollapsed=uncollapsed|collapsed}}}}\n        |list18= {{\u70bc\u91d1\u5de5\u4f5c\u5ba4/\u83f2\u8389\u4e1d\u7684\u5de5\u4f5c\u5ba4|child|{{#switch:{{{1}}}|\u83f2\u8389\u4e1d=uncollapsed|alluncollapsed=uncollapsed|collapsed}}}}\n}}\n}}"}}}