{"parse":{"title":"Talk:\u739b\u5c3c(\u739b\u5c3c\u548c\u5979\u7684\u670b\u53cb\u4eec)","pageid":242829,"wikitext":{"*":"== \u7b80\u4ecb\u597d\u5c11 ==\n\n<del>\u6caa\u6c5f\u6cf0\u8bed\u4e0a\u300a\u739b\u5c3c\u300b\u53ea\u6709\u6587\u5b57\u6ca1\u6709\u56fe\u7247\uff0c\u540c\u65f6\u4e5f\u4e0d\u5168\u3002{{\u9ed1\u5e55|\u300a\u57fa\u7840\u6cf0\u8bed\u300b\u4e4b\u7c7b\u6ca1\u6709\u6545\u4e8b\u6027\u5185\u5bb9\u7684\u6cf0\u8bed\u8bfe\u672c\u4e0d\u4f1a\u88ab\u6536\u8fdb\u6761\u76ee}}\u90a3\u739b\u5c3c\u7684\u80cc\u666f\u5185\u5bb9\u8981\u600e\u6837\u6269\u5145\uff1f\u2014\u2014<img src=\"//img.moegirl.org/common/avatars/58712/128.png\" style=\"width: 2.3em;border-radius: 50%;box-shadow: 1px 1px 2px 0px rgba(0, 0, 0, 0.45);\"/>&nbsp;[[User:Thaiyj123|\u6cf0\u56fd\u5a49\u59ec\ud83c\uddf9\ud83c\udded]] ([[User talk:Thaiyj123|\u0e1e\u0e39\u0e14\u0e04\u0e38\u0e22]]) 2017\u5e748\u67083\u65e5 (\u56db) 21:18 (CST)</del>"}}}