{"parse":{"title":"User:Mhz11235/Sandbox","pageid":206577,"wikitext":{"*":"{{Hide|\u6807\u9898=\u7acb\u7ed8|\u5185\u5bb9=\n{{{!}}class=\"wikitable\" style=\"text-align:center\"\n{{!}}-\n{{!}}width=\"33%\"{{!}}[[File:\u8429\u539f\u6714\u592a\u90ce\u7acb\u7ed81.png{{!}}x450px]]\n{{!}}width=\"33%\"{{!}}[[File:\u8429\u539f\u6714\u592a\u90ce\u7acb\u7ed82.png{{!}}x340px]]\n{{!}}width=\"34%\"{{!}}[[File:\u8429\u539f\u6714\u592a\u90ce\u7acb\u7ed83.png{{!}}x300px]]\n{{!}}-\n!\u901a\u5e38\n!\u6218\u6597\n!\u53d7\u4f24\uff08\u6218\u6597\u4e2d\uff09\n{{!}}- \n{{!}}[[File:\u8429\u539f\u6714\u592a\u90ce\u7acb\u7ed84.png{{!}}x300px]]\n{{!}}[[File:\u8429\u539f\u6714\u592a\u90ce\u7acb\u7ed85.png{{!}}x450px]]\n{{!}}[[File:\u8429\u539f\u6714\u592a\u90ce\u7acb\u7ed86.png{{!}}x450px]]\n{{!}}-\n!\u53d7\u4f24\uff08\u56fe\u4e66\u9986\uff09\n!\u8863\u88c5\u4e00\n!\u8863\u88c5\u56db\n{{!}}}\n}}"}}}