{"parse":{"title":"User:Sheep-realms/\u6c99\u76d2/\u7ea2\u8272\u8b66\u62123\u5355\u4f4d\u57fa\u7840\u6570\u636e","pageid":288288,"wikitext":{"*":"{{info\n|color=navy\n|leftimage=[[File:Commons-emblem-question_blue.svg|75px]]\n|\n<center><big><big>\u8fd9\u4e2a\u9875\u9762'''\u201c{{FULLPAGENAME}}\u201d'''\u662f{{color|red|\u88ab[[User:Sheep-realms|\u7ef5\u7f8a]]\u6b8b\u5fcd\u629b\u5f03}}\u7684\u7528\u6237\u6c99\u76d2</big></big></center>\n*\u8fd9\u4e2a\u9875\u9762\u5df2\u7ecf\u8fdb\u5316\u4e3a[[\u6a21\u677f:\u7ea2\u8272\u8b66\u62123\u5355\u4f4d\u6570\u636e]]\u3002\n*\u672c\u9875\u9762\u4ecd\u6709\u4e00\u5b9a\u7684\u53c2\u8003\u4ef7\u503c\uff0c\u8bf7\u4e0d\u8981\u4efb\u610f\u5220\u9664\u3002\n*\u9664\u7ef4\u62a4\u9700\u8981...\u4e0d\u5bf9\uff0c\u8fd9\u91cc\u4e0d\u53ef\u80fd\u518d\u66f4\u65b0\u4e86\uff01\n}}\n\n'''\u57fa\u672c\u6570\u636e'''\n\n\u79d1\u6280\u9700\u6c42\uff1a{{{\u79d1\u6280\u9700\u6c42|N/A}}}<br />\n\u7279\u6b8a\u80fd\u529b\uff1a{{{\u7279\u6b8a\u80fd\u529b|N/A}}}<br />\n\u662f\u5426\u4e24\u6816\uff1a{{{\u662f\u5426\u4e24\u6816|\u5426}}}<br />\n\u5efa\u9020\u82b1\u8d39\uff1a${{{\u5efa\u9020\u82b1\u8d39|N/A}}}<br />\n\u5efa\u9020\u65f6\u95f4\uff1a{{{\u5efa\u9020\u65f6\u95f4|N/A}}}\u79d2<br />\n\u751f\u547d\u6ee1\u503c\uff1a{{{\u751f\u547d\u6ee1\u503c|N/A}}}<br />\n\u79fb\u52a8\u901f\u5ea6\uff1a{{{\u79fb\u52a8\u901f\u5ea6|N/A}}}<br />\n\u78be\u538b\u7b49\u7ea7\uff1a{{{\u78be\u538b\u7b49\u7ea7|N/A}}}<br />\n\u6700\u5927\u5c04\u7a0b\uff1a{{{\u6700\u5927\u5c04\u7a0b|N/A}}}<br />\n\u6700\u5927\u89c6\u91ce\uff1a{{{\u6700\u5927\u89c6\u91ce|N/A}}}<br />\n\u4f24\u5bb3\u7c7b\u578b\uff1a{{{\u4f24\u5bb3\u7c7b\u578b|N/A}}}<br />\n\u5355\u53d1\u4f24\u5bb3\uff1a{{{\u5355\u53d1\u4f24\u5bb3|N/A}}}<br />\n\u5f00\u706b\u95f4\u9694\uff1a{{{\u5f00\u706b\u95f4\u9694|N/A}}}\u79d2<br />\n\u6bcf\u79d2\u4f24\u5bb3\uff1a{{{\u6bcf\u79d2\u4f24\u5bb3|N/A}}}<br />\n\u6e85\u5c04\u8303\u56f4\uff1a{{{\u6e85\u5c04\u8303\u56f4|N/A}}}<br />\n\u6e85\u5c04\u9012\u51cf\uff1a{{{\u6e85\u5c04\u9012\u51cf|N/A}}}<br />\n\u538b\u5236\u6570\u503c\uff1a{{{\u538b\u5236\u6570\u503c|N/A}}}<br />\n\u538b\u5236\u534a\u5f84\uff1a{{{\u538b\u5236\u534a\u5f84|N/A}}}<br />\n\u538b\u5236\u65f6\u95f4\uff1a{{{\u538b\u5236\u65f6\u95f4|N/A}}}\u79d2\n\n'''\u4f24\u5bb3\u4fee\u6b63'''\n\n\u67aa\u5f39\uff1a{{{\u67aa\u5f39|N/A}}}%<br />\n\u673a\u70ae\uff1a{{{\u673a\u70ae|N/A}}}%<br />\n\u72d9\u51fb\uff1a{{{\u72d9\u51fb|N/A}}}%<br />\n\u8089\u640f\uff1a{{{\u8089\u640f|N/A}}}%<br />\n\u706b\u7bad\uff1a{{{\u706b\u7bad|N/A}}}%<br />\n\u7834\u7247\uff1a{{{\u7834\u7247|N/A}}}%<br />\n\u7a7f\u7532\uff1a{{{\u7a7f\u7532|N/A}}}%<br />\n\u5149\u68f1\uff1a{{{\u5149\u68f1|N/A}}}%<br />\n\u7535\u51fb\uff1a{{{\u7535\u51fb|N/A}}}%<br />\n\u9ad8\u7206\uff1a{{{\u9ad8\u7206|N/A}}}%<br />\n\u9c7c\u96f7\uff1a{{{\u9c7c\u96f7|N/A}}}%<br />\n\u6bd2\u7d20\uff1a{{{\u6bd2\u7d20|N/A}}}%"}}}