{"parse":{"title":"User:\u4e5d\u6c5f\u6708/\u6362\u88c5\u6e38\u620f\u8bd5\u9a8c\u53f0","pageid":221039,"wikitext":{"*":"{{ #vardefine: puzzlei | 0 }}\n{{#while:\n|{{#ifexpr:{{#var:puzzlei}} < 5 | true }}\n|<div style=\"position:relative;margin:0;padding:0;height:143.2px;min-width:500px;\">{{#loop:puzzlej|0|5|\n{{hover|dis=inline-block\n|before=<div style=\"position:absolute;left:{{#expr:{{#var:puzzlej}}*100}}px;top:0;display:inline-block;opacity:0.1;\">{{image|\u663e\u793a\u7c7b\u578b=inline-block|\u56fe\u7247=107.jpg|resize=500\n|\u5bbd=100|\u9ad8=143.2\n|\u4e0a={{#expr:{{#var:puzzlei}}*143.2}}|\u4e0b=-{{#expr:{{#var:puzzlei}}*143.2}}\n|\u5de6={{#expr:{{#var:puzzlej}}*100}}|\u53f3=-{{#expr:{{#var:puzzlej}}*100}}\n}}</div>\n|after=<div style=\"position:absolute;left:{{#expr:{{#var:puzzlej}}*100}}px;border-radius:50%;\">{{image|\u663e\u793a\u7c7b\u578b=inline-block|\u56fe\u7247=107.jpg|resize=500\n|\u5bbd=100|\u9ad8=143.2\n|\u4e0a={{#expr:{{#var:puzzlei}}*143.2}}|\u4e0b=-{{#expr:{{#var:puzzlei}}*143.2}}\n|\u5de6={{#expr:{{#var:puzzlej}}*100}}|\u53f3=-{{#expr:{{#var:puzzlej}}*100}}\n}}</div>\n}}\n}}</div>{{#vardefine:puzzlei|{{#expr:{{#var:puzzlei}}+1}}}}}}"}}}