{"parse":{"title":"User:\u4e5d\u6c5f\u6708/\u6b4c\u66f2","pageid":238919,"wikitext":{"*":"{{#vardefine:index|1}}<!--\n-->{{#fornumargs:num\n|value\n|{{#switch:{{#var:value}}\n  |-={{#vardefine:index|{{#expr:{{#var:index}}+1}}}}{{#switch:{{#var:index}}\n    |4={{#switch:{{#var:type}}\n      |op|ed|in=\u8bdd\uff09\n      |ch=\uff09\n      |#default=surfix\uff09\n      }}\n    }}\n  |.=.\n  |,=\uff0c\n  |\u3001=\u3001\n  |#default={{#switch:{{#var:index}}\n    |1={{#switch:{{#var:value}}\n      |#default=*\u6b4c\u66f2\n      |op|\u4e3b\u9898\u66f2|\u7247\u5934\u66f2=*'''{{color|red|\u7247\u5934\u66f2\uff08OP\uff09'''}}{{#vardefine:type|op}}\n      |ed|\u7247\u5c3e\u66f2=*'''{{color|blue|\u7247\u5c3e\u66f2\uff08ED\uff09'''}}{{#vardefine:type|ed}}\n      |in|\u63d2\u5165\u66f2|\u5267\u4e2d\u6b4c=*'''{{color|orange|\u63d2\u5165\u66f2\uff08IN\uff09'''}}{{#vardefine:type|in}}\n      |ch|\u89d2\u8272\u6b4c=*'''{{color|green|\u89d2\u8272\u6b4c\uff08CH\uff09'''}}{{#vardefine:type|ch}}\n      }}{{#vardefine:index|{{#expr:{{#var:index}}+1}}}}\n    |2='''\u300a{{#var:value}}\u300b'''{{#switch:{{#var:type}}|op|ed|in=\uff08\u7b2c|ch=\uff08vol.|#default=prefix}}{{#vardefine:index|{{#expr:{{#var:index}}+1}}}}\n    |3={{#if:{{#var:value}}|{{#var:value}}}}\n    |#default={{#switch:{{#var:value}}\n      |#default=\n      }}\n    }}\n  }}\n}}\n\n== hello ==\n\nthis is a testtext --from moecraft"}}}