{"parse":{"title":"User:\u5343\u7384\u884d\u5e7b/\u9ec4\u6cb9","pageid":263302,"wikitext":{"*":"{{\u6807\u9898\u66ff\u6362|\u81ea\u7528\u65b0\u4f5c\u60c5\u62a5\u8868}}\n-{\n<!--\u540d\u79f0 || \u4f1a\u793e || \u7c7b\u522b || \u539f\u753b || \u811a\u672c || \u97f3\u4e50 || \u76d1\u7763 ||  CG ||  CV ||  OP ||  \u5b98\u7f51 || \u5b98\u63a8 || \u5907\u6ce8 || \u653e\u6d41 -->\n*\u4ec5\u6536\u5f55\u4e2a\u4eba\u89c9\u5f97\u6709\u8da3\u7684\uff0c\u57fa\u672c\u4e0d\u4f1a\u6536\u5f55ADV\u4ee5\u5916\u7684\u7c7b\u578b\uff0c\u4e0d\u6536\u5f55\u7eaf\u62d4/\u8fc7\u4e8e\u91cd\u53e3/\u590d\u523b\u7b49\u4f5c\u54c1\n*CG\u4e00\u680f\u5982\u65e0\u7279\u6b8a\u6ce8\u660e\u4e00\u822c\u7531\u539f\u753b\u517c\u4efb\n*\u7eff\u8272\u4e3a\u6807\u8bb0\uff0c\u84dd\u8272\u4e3a\u5185/\u5916\u94fe\uff0c\u7ea2\u8272\u4e3a\u8b66\u544a\n*\u6b22\u8fce\u6293\u866b\u3001\u8865\u5145\n*{{color|red|\u5bd2\u5047AFK\uff0c\u672c\u5217\u8868\u4e0d\u4f1a\u66f4\u65b0\uff0c\u6700\u540e\u66f4\u65b0\u4e8e12.26}}\n\n{| class=\"common-box mp-aliceblue plainlinks\"\n| class=\"common-box mp-linkico\" | \n\u5e38\u7528\u7f51\u7ad9\uff1a[http://www.2dfan.com/ hgamecn]{{\u00b7}}[http://bangumi.tv/ bgm]{{\u00b7}}[https://bbs4.2djgame.net/home/forum.php 2dj]{{\u00b7}}[https://bbs.zdfx.net/forum.php?mobile=no \u7ec8\u70b9]{{\u00b7}}[https://www.mygalgame.com/ \u5f1f\u5f1f]{{\u00b7}}[http://www.9moe.com/index.php 9moe]<br>[https://vndb.org/ vndb]{{\u00b7}}[http://holyseal.net/cgi-bin/newinfo.cgi?mode=file \u5723\u5c01]{{\u00b7}}[http://www.anime-sharing.com/forum/hentai-games-38/ A-S]{{\u00b7}}[https://erogamescape.dyndns.org/ \u6279\u8bc4\u7a7a\u95f4]{{\u00b7}}[http://www.jiku-chu.com/ \u8f74\u4e2d\u5fc3\u6d3e]{{\u00b7}}[http://getchu.com/ getchu]{{\u00b7}}[https://www.melonbooks.co.jp/soft/list.php?category_id=73#gnav \u751c\u74dc\u672c]<br>[http://erogetrailers.com/ \u60c5\u62a5\u6536\u96c6]{{\u00b7}}[http://seiya-saiga.com/game/lumpofsugar/kodomo.html \u8aa0\u4e5f]{{\u00b7}}[https://guide.ztzl.moe/ \u6795\u5957\u810f\u4e86]{{\u00b7}}{{\u00b7}}{{\u00b7}}\n----\n\u4f1a\u793e\uff1a[http://www.yuzu-soft.com/ \u67da\u5b50\u793e]{{\u00b7}}[http://august-soft.com/ \u516b\u6708\u793e]{{\u00b7}}[http://unisonshift.amusecraft.jp/ unisonshift]{{\u00b7}}[http://www.keromakura.net/ KeroQ/\u6795]{{\u00b7}}[http://www.angelnote.jp/ AngleNote]{{\u00b7}}[http://www.favo-soft.jp/soft/top.html Favorite\u793e]<br>[http://enishisoft.com/ \u3048\u306b\u3057\u305d\u3075\u3068]{{\u00b7}}[http://www.minori.ph/index_02.html \u4e2d\u4e8c\u793e]{{\u00b7}}[http://5pb.jp/ 5bp.]{{\u00b7}}[http://www.cuffs.co.jp/ cuffs]{{\u00b7}}[http://www.din.or.jp/~nekoneko/ \u732b\u732b\u793e]{{\u00b7}}[http://leaf.aquaplus.jp/ leaf]{{\u00b7}}[http://www.canxdensoft.net/index.php \u604b\u4e8c]{{\u00b7}}[http://www.web-giga.com/top/top.html \u620f\u753b][http://www.alicesoft.com/ Alice]{{\u00b7}}[http://www.lumpofsugar.co.jp/ \u65b9\u7cd6\u793e]<br>[http://www.alcot.biz/ Alcot]{{\u00b7}}[http://www.ensemble-game.com/ \u97f3\u7b26\u793e]{{\u00b7}}[http://www.noukano.com/top.php \u8111\u5185\u5f7c\u5973]{{\u00b7}}[http://key.visualarts.gr.jp/ key]{{\u00b7}}[http://sprite.org/ \u96ea\u78a7\u793e]{{\u00b7}}[http://www.illusion.co.jp/ I\u793e]{{\u00b7}}[http://www.hook-net.jp/smee/ smee]{{\u00b7}}{{\u00b7}}[http://www.clearrave.co.jp/ clearrave]{{\u00b7}}[http://circus-co.jp \u9a6c\u620f\u56e2]<br>[http://sagaplanets.product.co.jp/top.html saga]{{\u00b7}}[http://www.cuffs-cube.jp/ cuffs]{{\u00b7}}[http://www.a-kaguya.com/top.html \u7af9\u5b50\u793e]{{\u00b7}}[http://azarashi-soft.nexton-net.jp/ \u6d77\u8c79\u793e]{{\u00b7}}[http://www.eukleia.co.jp/eushully/main.html E\u793e]{{\u00b7}}[http://www.will-japan.co.jp/index.html will\u7cfb]{{\u00b7}}[http://5pb.jp/games/ 5pb.]{{\u00b7}}[http://www.omega-star.jp/ \u03c9star]{{\u00b7}}[https://www.nitroplus.co.jp/ N+]\n|}\n==2018\u5e747\u6708\uff0827\u65e5\uff09==\n{| class=\"wikitable\"\n|-\n! \u540d\u79f0 !! \u4f1a\u793e !! \u7c7b\u522b !! \u539f\u753b !! \u811a\u672c !! \u97f3\u4e50 !!\u76d1\u7763!! CG !! CV !! OP !! \u5b98\u7f51 !! \u5b98\u63a8 !! \u5907\u6ce8 !! \u653e\u6d41\n|-\n|Summer Pockets|| [[key]] || || Na-Ga\u3001\u548c\u6cc9\u3064\u3070\u3059\u3001\u6c38\u5c71\u3086\u3046\u306e\u3093 || [[\u65b0\u5c9b\u5915]]\u3001\u30cf\u30b5\u30de\u3001\u9b41|| \u6298\u6238\u4f38\u6cbb\u3001[[\u9ebb\u679d\u51c6]]\u3001\u3069\u3093\u307e\u308b\u3001\u7af9\u4e0b\u667a\u535a\u7b49 ||\u9b41  ||  ||  || ||  [http://key.visualarts.gr.jp/summer/ summer] ||[http://gs.dengeki.com/news/89671/ \u7535\u51fb\u59ec]|| {{color|red|\u65b0\u5c9b\u5915}}|| -\n|}\n==2018\u5e743\u6708\uff0830\u65e5\uff09==\n{| class=\"wikitable\"\n|-\n! \u540d\u79f0 !! \u4f1a\u793e !! \u7c7b\u522b !! \u539f\u753b !! \u811a\u672c !! \u97f3\u4e50 !!\u76d1\u7763!! CG !! CV !! OP !! \u5b98\u7f51 !! \u5b98\u63a8 !! \u5907\u6ce8 !! \u653e\u6d41\n|-\n|[[RIDDLE_JOKER]]||[[Yuzu-soft]]||\u5b66\u56edADV||[[\u5c0f\u821e\u4e00]]\u3001[[\u68a6\u7483\u51db]]\u3001[[\u83f0\u7ef5\u9065\u534e]]\uff08SD\uff09||\u5929\u5bae\u308a\u3064\u3001\u7825\u77f3\u5927\u6a39\u3001\u4fdd\u4f4f\u572d||Famishin\u3001Angel Note||\u5929\u5bae\u308a\u3064\uff08\u4f01\u5212\uff09\n||\u4e2d\u4e43\u3001\u30c8\u30df\u30d5\u30df\u3001\u30e2\u30c9\u30ad\u3055\u3093||\u6ca2\u6fa4\u7802\u7fbd\u3001\u304f\u3059\u306f\u3089\u3086\u3044\u3001\u9065\u305d\u3089\u3001\u82b1\u5712\u3081\u3044||||[http://www.yuzu-soft.com/products/riddle/index.html riddle]||[https://twitter.com/yuzusoft yuzusoft]||\u6211\u6c38\u8fdc\u559c\u6b22[[\u4e8c\u6761\u9662\u7fbd\u6708]]||-\n|-\n|\u6d88\u3048\u305f\u4e16\u754c\u3068\u6708\u3068\u5c11\u5973 || La\u2019cryma\u00d7\u3072\u3088\u3053\u30bd\u30d5\u30c8 || \u548c\u98a8\u4f1d\u5947\u30d5\u30a1\u30c3\u30b7\u30e7\u30f3\u30df\u30b9\u30c6\u30ea\u30fc || \u6708\u97f3 || \u795e\u591c\u512a ||  ||  ||   ||  ||  [https://www.bilibili.com/video/av16921914/ OP] ||  [http://hiyoko-soft.com/ hiyoko-soft] || [https://twitter.com/hiyokosoft hiyokosoft] || \u5b98\u7f51BGM\u6e17\u4eba\uff0c1\u6708\u8df33\u6708 || -\n|-\n|\u3053\u306d\u3053\u306d\u3053\u306d\u3053 || SkyFish poco || ADV || \u91ce\u7530\u3057\u3085\u306f\u3001\u30f2\u30ea\u3001\u306a\u3048\u306a\u3048 || \u5f18\u68ee\u9b5a\u3001\u4ed6 || \u97f3\u4e50 || \u76d1\u7763 ||  CG ||  CV ||  [http://erogetrailers.com/video/18699 OP] || [http://www.sky-fish.jp/sf-poco/koneko/index.htm koneko] || [https://twitter.com/SkyFish_san skyfish] || 23\u65e5 || \u653e\u6d41\n|}\n==2018\u5e742\u6708\uff0823\u65e5\uff09==\n{| class=\"wikitable\"\n|-\n! \u540d\u79f0 !! \u4f1a\u793e !! \u7c7b\u522b !! \u539f\u753b !! \u811a\u672c !! \u97f3\u4e50 !!\u76d1\u7763!! CG !! CV !! OP !! \u5b98\u7f51 !! \u5b98\u63a8 !! \u5907\u6ce8 !! \u653e\u6d41\n|-\n|\u3053\u3068\u306e\u306f\u30a2\u30e0\u30ea\u30e9\u30fc\u30c8 \u30b3\u30f3\u30d7\u30ea\u30fc\u30c8\u30d6\u30c3\u30af|| SukeraSparo || \u7eaf\u767e\u5408ADV ||  ||  ||  ||  ||  ||  || ||  [http://sukerasparo.com/ sukerasparo] || [https://twitter.com/sukerasparo sukerasparo]|| \u5168\u5e74\u9f84<br>\u5b8c\u5168\u7248 || -\n|-\n|\u30ed\u30b9\u30c8\u30fb\u30a8\u30b3\u30fc\u30ba||petit linge || \u6226\u56fd\u5f80\u9084\u308d\u307e\u3093\u305f\u3093ADV || \u7530\u5bae\u79cb\u4eba\u3001\u3042\u3093\u3053\u308d\u3082\u3061\u3001\u307f\u3064\u3044\u307e\u306a || \u685c\u57ce\u5341\u840c ||  ||  ||   ||  \u685c\u3042\u3044\u306d\u3001\u677e\u7530\u7406\u6c99\u3001\u840c\u82b1\u3061\u3087\u3053\u3001\u732b\u6751\u3086\u304d\u3001\u6210\u702c\u672a\u4e9c ||   || [https://www.petitlinge.net/main petitlinge] || [https://twitter.com/petitlinge petitlinge] || 2017\u6625 \u2192 <br>2017/07/28 \u2192<br> 2017/10/27 \u2192 2017/12/22 \u2192 <br>2018/01/26 \u2192 <br>2018/02/23 || -\n|}\n\n\n==2018\u5e741\u6708\uff0826\u65e5\uff09==\n{| class=\"wikitable\"\n|-\n! \u540d\u79f0 !! \u4f1a\u793e !! \u7c7b\u522b !! \u539f\u753b !! \u811a\u672c !! \u97f3\u4e50 !!\u76d1\u7763!! CG !! CV !! OP !! \u5b98\u7f51 !! \u5b98\u63a8 !! \u5907\u6ce8 !! \u653e\u6d41\n|-\n|\u30ea\u30a2\u30eb\u30a8\u30ed\u30b2\u30b7\u30c1\u30e5\u30a8\u30fc\u30b7\u30e7\u30f3\uff01 H\u00d73||\u81ea\u5b85\u3059\u305f\u3058\u304a ||\u62d4\u4f5cADV || || || || || || || ||[http://j-studio.net/reaero_h3/ reaero_h3]||[https://twitter.com/jitaku_st jitaku_st] ||FD\uff0c\u8df3\u7968\u81f31.26|| [http://j-studio.net/reaero_h3/special/trial/ \u4f53\u9a8c\u7248]\n|-\n|\u30b0\u30ea\u30b6\u30a4\u30a2 \u30d5\u30a1\u30f3\u30c8\u30e0\u30c8\u30ea\u30ac\u30fcvol.4 || \u30d5\u30ed\u30f3\u30c8\u30a6\u30a4\u30f3\u30b0 || \u5168\u5e74\u9f84ADV || \u6e21\u8fba\u660e\u592b\u3001\u306a\u306a\u304b\u307e\u3044\uff08SD\uff09 || \t\u85e4\u5d0e\u7adc\u592a ||{{color|green|\u677e\u672c\u6587\u7d00}}\u3001\u85e4\u9593\u4ec1||  ||   ||  [[\u5185\u7530\u771f\u793c]]\u3001[[\u4f50\u5009\u7dbe\u97f3]]\u3001[[\u540d\u585a\u4f73\u7e54]]\u3001[[\u79cd\u5d0e\u6566\u7f8e]] ||  [https://www.bilibili.com/video/av6889563/ \u524d\u4f5cPV] || [http://frontwing.jp/ http://frontwing.jp/] || {{en}}[https://twitter.com/FrontwingInt Frontwing] || steam\u5e94\u8be5\u4f1a\u540c\u671f\u4e0a\u67b6 || -\n|-\n|\u7e01\u308a\u3066\u6b64\u306e\u8449\u306f\u7d05\u306b|| [[Lump of Sugar]] ||  \u541b\u3068\u7e4b\u3050\u6155\u60c5\u6d6a\u6f2bADV|| \u840c\u6728\u539f\u3075\u307f\u305f\u3051\u3001\u594f\u30ca\u30b3\u30c8\uff08SD\uff09 || \u6c34\u6708\u7d17\u9ce5\u3001\u3066\u3064\u3058\u3093\u3001\u82b3\u4e95\u4e00||  ||  ||   ||  \u8305\u30f6\u5d0e\u30ea\u30ea\u30a3\u3001\u6843\u5c71\u3044\u304a\u3093\u3001\u6625\u4e43\u3044\u308d\u306f\u3001\u594f\u96e8 || [https://www.bilibili.com/video/av17006296/ OP] ||  [http://www.lumpofsugar.co.jp/product/yorikure/index.html yorikure] || [https://twitter.com/lumpofsuger lumpofsuger] || \u5907\u6ce8 || -\n|-\n|\u865a\u7a7a\u306e\u30d0\u30ed\u30c3\u30af || light ||  || \u4e0a\u7530\u30e1\u30bf\u30f2\u3001kAi/vi\uff08SD\uff09 || \u660f\u5f0f\u9f8d\u4e5f\u3001\u68ee\u9593\u307e\u308a\u3082 || {{color|green|\u6a0b\u53e3\u79c0\u6a39}}\u3001\u62bc\u4e0a\u6975 ||  ||   ||  \u4f50\u85e4\u6dbc\u6a39\u3001\u732b\u6751\u3086\u304d\u3001\u67ca\u9999\u793c\u3001\u6708\u91ce\u304d\u3044\u308d\u3001\u548c\u592e\u304d\u308a\u304b\u3001\u661f\u7fbd\u67da\u91cc || [https://www.bilibili.com/video/av16844733/ OP] ||  [http://www.light.gr.jp/light/top.html light] || [https://twitter.com/light_staff_tw light] ||\u521d\u56de\u9650\u5b9a\u8bbe\u5b9a\u96c6\u540c\u6346  || -\n|-\n| \u6dfb\u3044\u30ab\u30ce \uff5e\u304e\u3085\u3063\u3068\u62b1\u304d\u3057\u3081\u3066\uff5e|| \u622f\u753b || \u6dfb\u3044\u5bdd&\u30a4\u30c1\u30e3\u30e9\u30d6\u5b66\u5712ADV || \u3072\u3055\u307e\u304f\u307e\u3053\u3001{{color|green|\u3042\u3081\u3068\u3086\u304d}}\u3001\u5009\u6fa4\u3082\u3053\u3001\u3072\u306a\u305f\u3082\u3082 || \u6843\u91ce\u887f\u3001\u73b2\u3001\u3048\u3058\u3080\u3089 || \u5927\u5ddd\u8302\u4f38 ||  ||   ||  \u590f\u548c\u5c0f\u3001\u5fa1\u5b50\u67f4\u3053\u3088\u308a\u3001\u6b69\u30b5\u30e9\u3001\u6a58\u307e\u304a\u3001\u9234\u7530\u7f8e\u591c\u5b50\u3001\u53f6\u307f\u3086\u304d\u3001\u7acb\u82b1\u6c99\u7f85 || [https://www.bilibili.com/video/av15787729/ OP] || [http://products.web-giga.com/soikano/index.html soikano] || [https://twitter.com/web_giga giga] || \u8bbe\u5b9a\u96c6OST\u540c\u6346 || [http://products.web-giga.com/soikano/download.html \u4f53\u9a8c\u7248]\n|-\n|\u59b9\u3071\u3089\u3060\u3044\u3059\uff013 \uff5e\u304a\u5144\u3061\u3083\u3093\u30685\u4eba\u306e\u59b9\u306e\u3059\u3054\uff5e\u304f\uff01\u30a8\u30c3\u30c1\u3057\u307e\u304f\u308a\u306a\u6bce\u65e5\uff5e|| MOONSTONE Cherry  || \u59b9\u3068H\u3092\u3057\u307e\u304f\u308bADV|| \t\u65e5\u5411\u5948\u5c3e ||\u85e4\u4e95\u548c\u654f ||  || \u4f0a\u6771\u30e9\u30a4\u30d5 ||   || \t\u82b1\u6fa4\u3055\u304f\u3089\u3001\u7d50\u57ce\u307b\u306e\u304b\u3001\u8d64\u4e95\u30ea\u30a2\u3001\u6c34\u702c\u3086\u304d\u3001\u307f\u305f\u304b \u308a\u3093||  [https://www.bilibili.com/video/av15695035/ OP] || [http://www.moon-stone.jp/product/ms21/ ms21] || [https://twitter.com/moonstone_twitt moonstone] || \u524d\u4f5c\u811a\u672c[[\u548c\u6cc9\u4e07\u591c]] || [http://www.moon-stone.jp/product/ms21/ms21_download.html \u4f53\u9a8c\u7248]\n|-\n||\u5c06\u8ecd\u69d8\u306f\u304a\u5e74\u9803 || ALcot || \u5c06\u8ecd\u3084\u753a\u5a18\u3084\u304f\u30ce\u4e00\u3068\u30a4\u30c1\u30e3\u30e9\u30d6\u3059\u308b\u604b\u611b\u6642\u4ee3\u5287 || \u5e84\u540d\u6cc9\u77f3\u3001\u87f9\u5c4b\u3057\u304f\u3001\u3042\u304a\u306a\u307e\u3055\u304a\uff08SD\uff09 || \u7a7a\u4e0b\u5143\u3001\u5bae\u8535 || Peak A Soul+ ||  ||  \u771f\u5d0e\u30b1\u30a4 ||  \u82b1\u6fa4\u3055\u304f\u3089\u3001\u8305\u30f6\u5d0e\u30e1\u30a4\u3001\u4e0a\u539f\u3042\u304a\u3044\u3001\u307b\u305f\u308b ||   ||[http://www.alcot.biz/product/shogun/index.html shogun] ||  ||  || [http://www.9moe.com/read.php?tid=661270&sf=8e1&keyword=%BD%AB%DC%8A%98%94 \u4f53\u9a8c\u7248]\n|-\n|\u30a2\u30a4\u30ab\u30ae\uff5e\u30a2\u30d5\u30bf\u30fc\u30c7\u30a4\u30ba\uff5e|| \u3042\u3056\u3089\u3057\u305d\u3075\u3068 ||\u6065\u3058\u3089\u3044\u5e7c\u99b4\u67d3\u3068\u3082\u3063\u3068\u30c9\u30ae\u30de\u30ae\u540c\u68f2ADV || \u304e\u3093\u592a\u90ce || \u3082\u307f\u3042\u3052\u30eb\u30d1\u30f3R || {{color|green|\u91d1\u9589\u958b\u7f85\u5de7\u5922}}||  ||   ||  \u516b\u5c0b\u307e\u307f ||   ||  [http://azarashi-soft.nexton-net.jp/aikagiAD/ \u5b98\u7f51] || \u5b98\u63a8 || FD\uff0c\u5355\u5973\u4e3b || -\n|-\n|\u5c11\u5973\u3068\u5e74\u306e\u5dee\u3001\u3075\u305f\u307e\u308f\u308a\u3002 || \u3042\u304b\u3079\u3047\u305d\u3075\u3068\u3059\u308a\u3043 || \u5e74\u306e\u5dee\u604b\u611bADV ||  \u5965\u84ee\u30e1\u30ed || \u4e2d\u5cf6\u5927\u6cb3 ||  || \u4e2d\u5cf6\u5927\u6cb3 ||   ||  ||   ||  [http://www.akabeesoft3.com/products/tonofuta/index.html tonofuta] ||  || \u5fd8\u5e74\u4ea4 || [http://www.akabeesoft3.com/products/tonofuta/index.html \u4f53\u9a8c\u7248\u221a]\n|-\n|\u30c8\u30ea\u30ce\u30e9\u30a4\u30f3\uff1a\u30b8\u30a7\u30cd\u30b7\u30b9 || [[minori]] || ADV || \u304d\u306e\u3053\u306e\u307f\u3001\u67da\u5b50\u5948\u3072\u3088 || \u5fa1\u53a8\u307f\u304f\u308a\u3001\u82b1\u89c1\u7530\u3072\u304b\u308b\u30018\u3001\u94d7\u9e6d || \u5929\u95e8\u3001\u67f3\u82f1\u4e00\u6717 || \u9152\u4e95\u4f38\u548c ||   ||  ||  ||  [http://www.minori.ph/ minori] || - || FD || -\n|}\n\n\n==2017\u5e7412\u6708\uff0822\u65e5\uff09==\n{| class=\"wikitable\"\n|-\n! \u540d\u79f0 !! \u4f1a\u793e !! \u7c7b\u522b !! \u539f\u753b !! \u811a\u672c !! \u97f3\u4e50 !!\u76d1\u7763!! CG !! CV !! OP !! \u5b98\u7f51 !! \u5b98\u63a8 !! \u5907\u6ce8 !! \u653e\u6d41\n|-\u30af \n|\u604b\u30cb\u3001\u7518\u5473\u30f2\u30bd\u30a8\u30c6||CANVAS+GARDEN||\u540c\u4eba\u3001\u840c\u8c5aADV||\u5bae\u5742\u307f\u3086\u30fb\u306a\u3053||\u98a8\u9593\u307c\u306a\u3093\u3056\u3001\u9ad8\u5d8b\u6804\u4e8c||\u30d1\u30c8\u30ea\u30c1\u30a7\u30d5||||\u539f\u753b\u517c\u4efb||\u5922\u6708\u3084\u307f\u3001\u82b1\u6fa4\u3055\u304f\u3089\u3001<br>\u4e0a\u539f\u3042\u304a\u3044\u3001\u85e4\u4e43\u7406\u9999|| \u6642\u98a8\u8056\u591c\uff08\u6642\u306e\u5bbf\uff09||[http://www.canxdensoft.net/index.php canxdensoft]||[https://twitter.com/CANVAS_GARDEN CANVAS_GARDEN]||\u4f53\u9a8c\u724822\u65e5<br>\u6b63\u5f0f\u724831\u65e5||\u00d7\n|-\n|[[\u91d1\u8272LOVERICHE|\u91d1\u8272\u30e9\u30d6\u30ea\u30c3\u30c1\u30a7]]||[http://sagaplanets.product.co.jp/works/kinkoi/ SAGA PLANETS]||\u91d1\u8272\u5b66\u56edADV||\u307b\u3093\u305f\u306b\u304b\u306a\u3048\u3001\u3068\u3089\u306e\u3059\u3051\u3001\u3074\u3053\u3074\u3053\u3050\u3089\u3080\uff08SD\uff09||\u3055\u304b\u304d\u5098||Arte Refact\u3001\u677e\u672c\u614e\u4e00\u90ce\u3001\u6a0b\u53e3\u79c0\u6a39\u3001\u6c34\u6708\u9675||\uff2b\uff55\uff52\uff4f||||\u732b\u6751\u3086\u304d\u3001\u9065\u305d\u3089\u3001\u3042\u3058\u79cb\u5200\u9c7c\u3001\u5c0f\u9ce5\u5c45\u5915\u82b1\u3001\u79cb\u91ce\u82b1\u3001\u571f\u5c4b\u7c98\u3001\u98a8\u97f3||[http://www.bilibili.com/video/av14467065/index_1.html yo-yu (feat.works)]||[http://sagaplanets.product.co.jp/works/kinkoi/index.html kinkoi]||[https://twitter.com/SAGAPLANETS SAGAPLANETS]||||[http://www.9moe.com/read.php?tid=663100&sf=404 \u221a]\n|-\n|Pure Marriage \uff5e\u8d64\u3044\u7cf8\u7269\u8a9e \u3055\u304f\u3089\u7de8\uff5e ||Lass Pixy ||\u3061\u3087\u3063\u3068\u305b\u3064\u306a\u3044\u7d14\u611b\u30ad\u30e5\u30f3\u7518ADV||\u53e4\u5ddd\u308c\u3082\u3093\u3001\u68ee\u5c71\u3057\u3058\u307f||\u5263\u6280\u30de\u30ca||   ||  ||  || \u5e83\u702c\u9999\u83dc\u3001\u85e4\u4e43\u7406\u9999\u3001\u5922\u6708\u3084\u307f\u3001\u674f\u82b1|| || [http://lass.jp/lasspixy/puremarriage/sakura/index.html sakura]||[https://twitter.com/lasspixy_offi lasspixy_offi]||\u901a\u5e38\u7248\u4fbf\u5b9c\u7684\u8981\u6b7b||[https://sukebei.nyaa.si/view/2408961 \u221a]\n|-\n|\u7720\u308c\u306c\u7f8a\u3068\u5b64\u72ec\u306a\u72fc<br> \uff0dA Tale of Love\uff0c and Cutthroat\uff0d||CLOCKUP||\u30ed\u30de\u30f3\u30ce\u30ef\u30fc\u30ebADV||\u306e\u308a\u3056\u306d||\u660f\u5f0f\u9f8d\u4e5f\u3001\u52dd\u5c71\u9f8d\u592a\u90ce|| || \u963f\u4e45\u6d25\u4eae || \u82b1\u7b20\u30df\u30c5\u30ad||\n || ||[http://clockup.net/yourou/ yourou]||[https://twitter.com/clockupofficial clockupofficial] || ||[https://sukebei.nyaa.si/view/2408794 \u221a]\n|-\n|\u30a2\u30de\u30ab\u30ce \uff5eSecond Season\uff5e+ || \u3042\u3056\u3089\u3057\u305d\u3075\u3068 || \u3082\u3063\u3068\u3044\u3063\u3071\u3044\u7518\u3048\u305f\u3044\u5f7c\u5973\u3068\u4ffa\u306e\u7d14\u611bADV || \u30d4\u30ed\u6c34\u3001\u831c\u5c4b\uff08SD\u539f\u753b\uff09 || \u9f8d\u5cb3\u6765 || \u97f3\u4e50 || \u3042\u304a\u304d\u3085\u3093 ||  || \u6ce2\u5948\u675f\u98a8\u666f\u3001\u6843\u5c71\u3044\u304a\u3093\u3001\u677e\u7530\u7406\u6c99\u3001\u4e00\u8272\u30d2\u30ab\u30eb ||   ||  [http://azarashi-soft.nexton-net.jp/amakano2+/ amakano2+] || [https://twitter.com/AzarashiSoft AzarashiSoft] || FD || [http://www.9moe.com/read.php?tid=663101&sf=4f4 \u221a]\n|-\n|\u6708\u306b\u5bc4\u308a\u305d\u3046\u4e59\u5973\u306e\u4f5c\u6cd52.2 A\u00d7L+SA!! || Navel || \u604b\u611bADV || \u9234\u5e73\u3072\u308d\u3001\u897f\u53c8\u8475\u3001\u767d\u7fbd\u5948\u5c3e\uff08SD\uff09\u3001\u7fbd\u7d14\u308a\u304a\uff08SD\uff09\u3001\u3054\u308d\u3046\uff08SD\uff09 || \u6771\u30ce\u52a9 || Arte Refact || \u76d1\u7763 ||   ||  CV ||  Uaq5E-oNgj0  ||  [http://www.project-navel.com/tsukiniyorisou_2nd_alsa/ 2.2] || [https://twitter.com/project_navel project_navel] || 2.2 || [http://www.9moe.com/read.php?tid=663809&sf=818&keyword=2.2 \u221a]\n|-\n|\u666f\u306e\u6d77\u306e\u30a2\u30da\u30a4\u30ea\u30a2FD \uff5e\u30ab\u30b5\u30d6\u30e9\u30f3\u30ab\u306e\u9a0e\u58eb\uff5e || \u30b7\u30eb\u30ad\u30fc\u30ba\u30d7\u30e9\u30b9 DOLCE || \u604b\u3068\u9752\u6625\u306e\u79d1\u5b66\u5192\u967a\u30d5\u30a1\u30f3\u30bf\u30b8\u30fc\u30a2\u30c9\u30d9\u30f3\u30c1\u30e3\u30fc\u30b2\u30fc\u30e0\u306e\u30d5\u30a1\u30f3\u30c7\u30a3\u30b9\u30af || \u3044\u3064\u3044 || \u7bc4\u4e43\u79cb\u6674 ||  || \u7bc4\u4e43\u79cb\u6674\uff08\u4f01\u5212\uff09 ||   ||  \u79cb\u91ce\u82b1\u3001\u6a58\u307e\u304a\u3001\u5c0f\u9ce5\u5c45\u5915\u82b1\u3001\u624b\u585a\u308a\u3087\u3046\u3053\u3001\u6b69\u30b5\u30e9\u3001\u690d\u6728\u51cc\u4ea8 ||  ||  [http://www.silkysplus.jp/game/apeiria/another_story.html apeiria] ||[https://twitter.com/silkysplus silkysplus]|| \uff26\uff24 || [https://sukebei.nyaa.si/view/2408796 \u221a]\n|-\n|\u622f\u30a3\u7259 \uff5e\u30d5\u30a1\u30f3\u30ea\u30e5\u30fc\u30b2\u2020\u30af\u30ea\u30d5\u30a9\u30c8\uff5e|| LiLiM || \u652f\u914d\u306b\u3088\u308b\u4e0d\u5747\u8861\u306a\u8c9e\u7bc0\u3068\u8840\u3092\u5de1\u308bADV || \u91d1\u76ee\u9bdb\u3074\u3093\u304f\u3001\u6850\u5cf6\u5343\u591c\uff08\u7537\u6027\uff09 || \u516d\u82b1\u68a8\u82b1 ||  ||  ||  ||  \u661f\u7a7a\u30e6\u30e1\u3001\u7dbe\u702c\u3042\u304b\u308a\u3001\u552f\u9999\u3001\u91ce\u3005\u6751\u7d17\u591c ||  b95vRxGyObk  ||  [http://s-digi.jp/lilim/02_soft/01_lilim/20_giiga/index.html giiga] ||[http://lilimstafblog.blog16.fc2.com/ \u535a\u5ba2] ||{{color|red|NTR}}  || [https://sukebei.nyaa.si/view/2408798 \u221a]\n|-\n|\u306a\u3061\u3085\u3089\u308b\u3070\u3051\u30fc\u3057\u3087\u3093 || hibiki works ||  \u305a\u3063\u3068\u5fc3\u306b\u6b8b\u308b\u590f\u306e\u521d\u604bADV ||   \u6d45\u6d77\u671d\u7f8e || \u6c34\u702c\u62d3\u672a\u3001\u4e2d\u5cf6\u5927\u6cb3 || \u897f\u5742\u606d\u5e73 ||  || || \u82b1\u6fa4\u3055\u304f\u3089\u3001\u67da\u539f\u307f\u3046||   || [http://www.hibiki-site.com/natural_vacation/ natural_vacation] ||  || \u59d0\u59b9\u4e3c || [http://www.9moe.com/read.php?tid=663126&sf=b6e \u221a]\n|-\n|\u5e55\u672b \u5c3d\u5fe0\u5831\u56fd\u70c8\u58eb\u4f1d MIBURO || \u30a4\u30f3\u30ec  || \u5e55\u672b\u8840\u7159\u6d3b\u5287 || \u306c\u3044\u3001\u3072\u3063\u3055\u3064\u304f\u3093 || \u8449\u5c71\u3053\u3088\u30fc\u3066 || Elements Garden||  ||   ||  \u4e1a\u754c\u5927\u534a ||  [https://www.bilibili.com/video/av17522290/ OP] ||  [http://inre-soft.com/miburo/index.html miburo] || [https://twitter.com/inre_official inre_official] || OP\u30fbED\u30de\u30ad\u30b7\u30b7\u30f3\u30b0\u30eb\u3001\u8a2d\u5b9a\u96c6\u540c\u6346 || \n|}\n==\u672a\u5b9a==\n{| class=\"wikitable\"\n|-\n! \u540d\u79f0 !! \u4f1a\u793e !! \u7c7b\u522b !! \u539f\u753b !! \u811a\u672c !! \u97f3\u4e50 !!\u76d1\u7763!! CG !! CV !! OP !! \u5b98\u7f51 !! \u5b98\u63a8 !! \u5907\u6ce8 !! \u653e\u6d41\n|-\n|\u7d20\u6674\u3089\u3057\u304d\u56fd\u5bb6\u306e\u7bc9\u304d\u65b9\uff08\u7565\u79f0\u3059\u3070\u3053\uff09||\u30a2\u30a4\u30ea\u30b9\u30d5\u30a3\u30fc\u30eb\u30c9||\u540c\u4ebaRPG||||||||||||||||[http://irisfieldcreate.blog.fc2.com/ blog]||[https://twitter.com/tukudani_iris tukudani_iris]||||-\n|-\n|\u3055\u304f\u3089\u3001\u3082\u3086\u3002-as the Night's, Reincarnation- || [[Favorite]] || ADV || \u53f8\u7530\u30ab\u30ba\u30d2\u30ed\u3001\u306a\u3064\u3081\u3048\u308a\u3001\u30df\u30ba\u30bf\u30de(SD) || \u6f06\u539f\u96ea\u4eba || [[\u5fcd(\u97f3\u4e50\u5bb6)|\u5fcd]] ||  ||   ||  ||   ||  [http://www.favo-soft.jp/soft/top.html Favorite] || [https://twitter.com/favo_official favo_official] || [http://bbs.ngacn.cc/read.php?tid=13108912 \u5e7c\u9a6f\u67d3+\u524d\u9b54\u6cd5\u5c11\u5973] || -\n|}\n}-\n{{Template:Galgame\u516c\u53f8|\u6298\u53e0}}"}}}