{"parse":{"title":"User:\u7e54\u661f\u846c","pageid":241261,"wikitext":{"*":"<center>\n<div style=\"background: #fff; border: 1px solid #000000; width:10cm; min-height:150px; position:relative; border-radius:0.75em; width: 50%;\">\n<div style=\"background: #000; overflow: hidden; border-radius:0.5em; text-align:center; border: 1px solid #000000; font-side: 110%; font-weight: bold; color: white;margin-top:5px; \">''\u81ea\u6211\u4ecb\u7ecd''</div>\n<div style=\" text-align:center; background: #ffffff;margin-top:0px; padding-right: 5px; padding-top: 9px; border-radius:0.75em;\">\n\u4e00\u4f4d\u559c\u6b22\u6765\u840c\u767e\u901b\u901b\u7684\u665a\u8f88\u3002\u5bf9\u5c11\u90e8\u5206\u7684\u4e8b\u662f\u5fc3\u8840\u6765\u6f6e\u7684\u3002<br/>\u4e60\u60ef\u7528\u7e41\u4f53\u5b57\uff0c\u4e3a\u4e86\u66f4\u597d\u7684\u878d\u5165\uff0c\u9009\u62e9\u7528\u7b80\u4f53\u5b57\u3002<br/>\u559c\u6b22\u5f88\u591a\u524d\u8f88\uff0c\u5176\u4e2d\u6700\u4e2d\u610f\u7684\u524d\u8f88\u6709\uff1a[[User:\u5b87\u6587\u5929\u542f|\u5b87\u6587\u524d\u8f88]]\u3001[[User:\u65f6\u95f4\u306e\u795e-\u4f18\u6ce0|\u5341\u516d\u524d\u8f88]]\u3001[[User:\u4e91\u971e|\u55b5]]\u3001[[User:\u6b92\u6052\u539f\u7f6a|\u539f\u7f6a]]\u3002<br/>\u5176\u4e2d\u2014\u2014<br/>\u5b87\u6587\u524d\u8f88\u544a\u8bc9\u4e86\u6211\u5f88\u591a\u4e8b\u3002<br/>\u5341\u516d\u524d\u8f88\u6709\u95ee\u5fc5\u7b54\u3002<br/>\u55b5\u548c\u6211\u8bb2\u4e86\u5f88\u591a\u9ad8\u5927\u4e0a\u7684\u4e8b\u3002<br/>\u81f3\u4e8e\u539f\u7f6a\u548c\u6211\u8bf4\u4e86\u8d8a\u6765\u8d8a\u591a\u7684\u4e8b\u4e0e\u6559\u4f1a\u4e86\u6211\u5f88\u591a\u4e8b\u3002\n</div>\n</div>\n</center>\n\n----\n'''\u6709\u7528'''\n*[[User:\u4e91\u971e/\u7f16\u8f91\u95f2\u8c08|\u7f16\u8f91\u95f2\u8c08]]\n*[[User:\u6b92\u6052\u539f\u7f6a/\u7f16\u8f91\u542f\u793a\u5f55|\u7f16\u8f91\u542f\u793a\u5f55]]"}}}